package/__init__.py
package/downgit.py
package/setup.py
downgit-2.1.dist-info/METADATA
downgit-2.1.dist-info/WHEEL
downgit-2.1.dist-info/entry_points.txt
downgit-2.1.dist-info/top_level.txt
downgit-2.1.dist-info/RECORD
