Metadata-Version: 2.1
Name: downgit
Version: 2.1
Summary: Download any subdirectory or file from GitHub repository
Home-page: https://github.com/Propsi4/DownGitCMD
Author: Propsi4
Author-email: gaenday12@gmail.com
License: MIT
Keywords: downgit,download exact repo,github,download folder from repo,download file from repo
Requires-Dist: certifi >=2023.7.22
Requires-Dist: charset-normalizer >=3.3.2
Requires-Dist: colorama >=0.4.6
Requires-Dist: idna >=3.4
Requires-Dist: requests >=2.31.0
Requires-Dist: tqdm >=4.66.1
Requires-Dist: urllib3 >=2.0.7
